stack/__init__.py
stack.py-2.0.dist-info/LICENSE
stack.py-2.0.dist-info/METADATA
stack.py-2.0.dist-info/WHEEL
stack.py-2.0.dist-info/top_level.txt
stack.py-2.0.dist-info/RECORD
