Metadata-Version: 2.1
Name: stack.py
Version: 2.0
Summary: LIFO Stack & FIFO Queue Implementation in Python.
Home-page: https://github.com/FireHead90544/stack.py
Author: Rudransh Joshi
Author-email: rudranshjoshi1806@gmail.com
License: Apache License 2.0
Project-URL: Issue tracker, https://github.com/FireHead90544/stack.py/issues
Platform: any
License-File: LICENSE
